esther_scale_out/__init__.py
esther_scale_out/manage.py
esther_scale_out-0.1.13.dist-info/METADATA
esther_scale_out-0.1.13.dist-info/WHEEL
esther_scale_out-0.1.13.dist-info/entry_points.txt
esther_scale_out-0.1.13.dist-info/top_level.txt
esther_scale_out-0.1.13.dist-info/RECORD
