Metadata-Version: 2.1
Name: esther_scale_out
Version: 0.1.13
Summary: Default template for PDM package
Author-email: EstherCho-7 <dkgkqm777@gmail.com>
License: MIT
Requires-Python: >=3.11
Requires-Dist: psutil>=6.1.0
Requires-Dist: requests
